hpecp/__init__.py
hpecp/base_resource.py
hpecp/catalog.py
hpecp/cli_utils.py
hpecp/client.py
hpecp/config.py
hpecp/datatap.py
hpecp/epic_worker.py
hpecp/exceptions.py
hpecp/gateway.py
hpecp/install.py
hpecp/k8s_cluster.py
hpecp/k8s_worker.py
hpecp/license.py
hpecp/lock.py
hpecp/logger.py
hpecp/role.py
hpecp/tenant.py
hpecp/user.py
hpecp/cli/__init__.py
hpecp/cli/base.py
hpecp/cli/catalog.py
hpecp/cli/config.py
hpecp/cli/datatap.py
hpecp/cli/epicworker.py
hpecp/cli/gateway.py
hpecp/cli/httpclient.py
hpecp/cli/install.py
hpecp/cli/k8scluster.py
hpecp/cli/k8sworker.py
hpecp/cli/license.py
hpecp/cli/lock.py
hpecp/cli/role.py
hpecp/cli/tenant.py
hpecp/cli/user.py
hpecp-0.22.13.data/scripts/hpecp
hpecp-0.22.13.dist-info/LICENSE
hpecp-0.22.13.dist-info/METADATA
hpecp-0.22.13.dist-info/WHEEL
hpecp-0.22.13.dist-info/top_level.txt
hpecp-0.22.13.dist-info/RECORD
